omgeo/__init__.py
omgeo/geocoder.py
omgeo/places.py
omgeo/postprocessors.py
omgeo/preprocessors.py
omgeo/processor.py
omgeo/services/__init__.py
omgeo/services/base.py
omgeo/services/bing.py
omgeo/services/esri.py
omgeo/services/google.py
omgeo/services/mapquest.py
omgeo/services/nominatim.py
omgeo/services/pelias.py
omgeo/services/us_census.py
omgeo/tests/__init__.py
omgeo/tests/tests.py
python_omgeo-6.2.2.dist-info/LICENSE.txt
python_omgeo-6.2.2.dist-info/METADATA
python_omgeo-6.2.2.dist-info/WHEEL
python_omgeo-6.2.2.dist-info/top_level.txt
python_omgeo-6.2.2.dist-info/RECORD
