Metadata-Version: 2.1
Name: python-omgeo
Version: 6.2.2
Summary: Geocoding Library using ESRI, Google, Bing Maps, US Census, OpenStreetMap, Pelias, and MapQuest geocoders
Home-page: http://github.com/azavea/python-omgeo
Author: Azavea, Inc.
Author-email: info@azavea.com
License: MIT
Classifier: Development Status :: 4 - Beta
Classifier: License :: OSI Approved :: MIT License
Classifier: Topic :: Scientific/Engineering :: GIS
Classifier: Programming Language :: Python :: 2.7
Classifier: Programming Language :: Python :: 2.6
Classifier: Programming Language :: Python :: 3
License-File: LICENSE.txt
Requires-Dist: requests >=2.18
